SaraikiNLP/__init__.py
SaraikiNLP/normalization.py
SaraikiNLP/preprocessing.py
saraikinlp-0.1.12.dist-info/licenses/LICENSE.md
saraikinlp-0.1.12.dist-info/METADATA
saraikinlp-0.1.12.dist-info/WHEEL
saraikinlp-0.1.12.dist-info/top_level.txt
saraikinlp-0.1.12.dist-info/RECORD
