Metadata-Version: 2.4
Name: SaraikiNLP
Version: 0.1.12
Summary: SaraikiNLP: The Python NLP Framework for Saraiki Language Research
Author: MMuzamilAI
License: MIT License
Keywords: saraiki,saraiki nlp,saraikinlp,machine learning,text pre-processing,nlp,low resource language,pakistani languages,nlp framework,underrated languages
Classifier: Intended Audience :: Developers
Classifier: Intended Audience :: Education
Classifier: Intended Audience :: Science/Research
Classifier: License :: OSI Approved :: MIT License
Classifier: Operating System :: MacOS :: MacOS X
Classifier: Operating System :: Microsoft :: Windows
Classifier: Operating System :: POSIX :: Linux
Classifier: Programming Language :: Python :: 3.6
Classifier: Programming Language :: Python :: 3.7
Classifier: Programming Language :: Python :: 3.8
Classifier: Programming Language :: Python :: 3.9
Classifier: Programming Language :: Python :: 3.10
Classifier: Programming Language :: Python :: 3.11
Classifier: Programming Language :: Python :: 3.12
Classifier: Topic :: Software Development :: Libraries
Classifier: Topic :: Software Development :: Libraries :: Python Modules
Classifier: Topic :: Text Processing :: Linguistic
Requires-Python: >=3.6
License-File: LICENSE.md
Dynamic: license-file
